build/lib/flet_manager/__init__.py
build/lib/flet_manager/app.py
build/lib/flet_manager/utils/__init__.py
build/lib/flet_manager/utils/client.py
build/lib/flet_manager/utils/font.py
build/lib/flet_manager/utils/get_svg.py
build/lib/flet_manager/utils/themes.py
build/lib/flet_manager/views/__init__.py
build/lib/flet_manager/views/base.py
build/lib/flet_manager/views/error.py
build/lib/flet_manager/views/main.py
flet_manager/__init__.py
flet_manager/app.py
flet_manager/utils/__init__.py
flet_manager/utils/client.py
flet_manager/utils/font.py
flet_manager/utils/get_svg.py
flet_manager/utils/themes.py
flet_manager/views/__init__.py
flet_manager/views/base.py
flet_manager/views/error.py
flet_manager/views/main.py
flet_manager-0.3.4.dist-info/LICENSE
flet_manager-0.3.4.dist-info/METADATA
flet_manager-0.3.4.dist-info/WHEEL
flet_manager-0.3.4.dist-info/top_level.txt
flet_manager-0.3.4.dist-info/RECORD
