Metadata-Version: 2.1
Name: flet-manager
Version: 0.3.4
Home-page: https://yegoryakubovich.com
Author: Yegor Yakubovich
Author-email: personal@yegoryakubovich.com
License: Apache 2.0
Classifier: Intended Audience :: Developers
Classifier: License :: OSI Approved :: Apache Software License
Classifier: Programming Language :: Python
Classifier: Operating System :: OS Independent
Requires-Python: >=3.7
License-File: LICENSE
Requires-Dist: flet
Requires-Dist: flet-fastapi
